Metadata-Version: 2.1
Name: async-cleverbot
Version: 0.2.2
Summary: Asyncio API wrapper for the Travitia Cleverbot API. (https://public-api.travitia.xyz/talk)
Home-page: https://github.com/crrapi/async-cleverbot
Author: crrapi
License: MIT
Platform: UNKNOWN
Classifier: Programming Language :: Python :: 3.5
Classifier: Programming Language :: Python :: 3.6
Classifier: Programming Language :: Python :: 3.7
Classifier: Programming Language :: Python :: 3.8
Classifier: License :: OSI Approved :: MIT License
Classifier: Operating System :: OS Independent
